odoo/addons/mrp_stock_analytic/README.rst
odoo/addons/mrp_stock_analytic/__init__.py
odoo/addons/mrp_stock_analytic/__manifest__.py
odoo/addons/mrp_stock_analytic/i18n/it.po
odoo/addons/mrp_stock_analytic/i18n/mrp_stock_analytic.pot
odoo/addons/mrp_stock_analytic/models/__init__.py
odoo/addons/mrp_stock_analytic/models/mrp_production.py
odoo/addons/mrp_stock_analytic/readme/CONFIGURE.md
odoo/addons/mrp_stock_analytic/readme/CONTRIBUTORS.md
odoo/addons/mrp_stock_analytic/readme/DESCRIPTION.md
odoo/addons/mrp_stock_analytic/readme/USAGE.md
odoo/addons/mrp_stock_analytic/static/description/icon.png
odoo/addons/mrp_stock_analytic/static/description/index.html
odoo/addons/mrp_stock_analytic/tests/__init__.py
odoo/addons/mrp_stock_analytic/tests/test_mrp_stock_analytic.py
odoo/addons/mrp_stock_analytic/views/mrp_production_views.xml
odoo_addon_mrp_stock_analytic-17.0.1.0.0.6.dist-info/METADATA
odoo_addon_mrp_stock_analytic-17.0.1.0.0.6.dist-info/WHEEL
odoo_addon_mrp_stock_analytic-17.0.1.0.0.6.dist-info/top_level.txt
odoo_addon_mrp_stock_analytic-17.0.1.0.0.6.dist-info/RECORD
